<org.simbrain.world.threedworld.ThreeDWorld>
  <preferences>
    <sceneName></sceneName>
    <guiName></guiName>
    <width>630</width>
    <height>461</height>
    <realTimeMode>true</realTimeMode>
    <frameRate>30</frameRate>
    <ambientLight>-1</ambientLight>
    <directionalLight>-1</directionalLight>
    <fieldOfView>80.0</fieldOfView>
    <nearClip>0.1</nearClip>
    <farClip>100.0</farClip>
    <moveSpeed>5.0</moveSpeed>
    <rotateSpeed>10.0</rotateSpeed>
    <zoomSpeed>1.0</zoomSpeed>
  </preferences>
  <engine/>
  <entities/>
  <idCounter>
    <value>1</value>
  </idCounter>
</org.simbrain.world.threedworld.ThreeDWorld>